ALASutils/__init__.py
ALASutils/sourcextractor.py
ALASutils/utils.py
ALASutils-0.0.13.dist-info/LICENSE
ALASutils-0.0.13.dist-info/METADATA
ALASutils-0.0.13.dist-info/WHEEL
ALASutils-0.0.13.dist-info/top_level.txt
ALASutils-0.0.13.dist-info/RECORD
